gen3/__init__.py
gen3/auth.py
gen3/cli/__init__.py
gen3/cli/__main__.py
gen3/cli/auth.py
gen3/cli/configure.py
gen3/cli/discovery.py
gen3/cli/drs_pull.py
gen3/cli/file.py
gen3/cli/nih.py
gen3/cli/objects.py
gen3/cli/pfb.py
gen3/cli/users.py
gen3/cli/wrap.py
gen3/cli/wss.py
gen3/configure.py
gen3/discovery_dois.py
gen3/doi.py
gen3/external/__init__.py
gen3/external/external.py
gen3/external/nih/__init__.py
gen3/external/nih/dbgap_doi.py
gen3/external/nih/dbgap_fhir.py
gen3/external/nih/dbgap_study_registration.py
gen3/external/nih/utils.py
gen3/file.py
gen3/index.py
gen3/jobs.py
gen3/metadata.py
gen3/object.py
gen3/query.py
gen3/submission.py
gen3/tools/__init__.py
gen3/tools/bundle/ingest_manifest.py
gen3/tools/diff.py
gen3/tools/download/__init__.py
gen3/tools/download/drs_download.py
gen3/tools/download/drs_resolvers.py
gen3/tools/download/external_file_download.py
gen3/tools/expansion.py
gen3/tools/indexing/__init__.py
gen3/tools/indexing/download_manifest.py
gen3/tools/indexing/index_manifest.py
gen3/tools/indexing/merge_manifests.py
gen3/tools/indexing/post_indexing_validation.py
gen3/tools/indexing/validate_manifest_format.py
gen3/tools/indexing/verify_manifest.py
gen3/tools/merge.py
gen3/tools/metadata/__init__.py
gen3/tools/metadata/crosswalk.py
gen3/tools/metadata/discovery.py
gen3/tools/metadata/discovery_objects.py
gen3/tools/metadata/ingest_manifest.py
gen3/tools/metadata/verify_manifest.py
gen3/tools/utils.py
gen3/tools/wrap.py
gen3/utils.py
gen3/wss.py
gen3-4.27.5.dist-info/METADATA
gen3-4.27.5.dist-info/WHEEL
gen3-4.27.5.dist-info/entry_points.txt
gen3-4.27.5.dist-info/licenses/LICENSE
gen3-4.27.5.dist-info/licenses/NOTICE
gen3-4.27.5.dist-info/RECORD
